checksum.py
color.py
logger/__init__.py
logger/formatter.py
project_pkgs-0.0.6.dist-info/LICENSE
project_pkgs-0.0.6.dist-info/METADATA
project_pkgs-0.0.6.dist-info/WHEEL
project_pkgs-0.0.6.dist-info/top_level.txt
project_pkgs-0.0.6.dist-info/RECORD
